pyADfit/__init__.py
pyADfit/disc_fit.py
pyADfit/disc_launch.py
pyADfit/disc_model.py
pyADfit-0.0.2.dist-info/LICENSE
pyADfit-0.0.2.dist-info/METADATA
pyADfit-0.0.2.dist-info/WHEEL
pyADfit-0.0.2.dist-info/top_level.txt
pyADfit-0.0.2.dist-info/RECORD
