Metadata-Version: 2.1
Name: pyADfit
Version: 0.0.2
Summary: A nested sampling approach to quasi-stellar object (QSO) accretion disc fitting.
Author-email: Fabio Rigamonti <fabio.rigamonti@inaf.it>, Luca Ighina <luca.ighina@inaf.it>
Project-URL: Homepage, https://github.com/FabioRigamonti/pyADfit
Project-URL: Issues, https://github.com/FabioRigamonti/pyADfit/issues
Classifier: Programming Language :: Python :: 3
Classifier: License :: OSI Approved :: MIT License
Classifier: Operating System :: OS Independent
Requires-Python: >=3.8
License-File: LICENSE
Requires-Dist: numpy >=1.24.4
Requires-Dist: scipy >=1.10.1
Requires-Dist: matplotlib >=3.7.5
Requires-Dist: raynest >=1.0.2
Requires-Dist: CPNest >=0.11.5
Requires-Dist: nessai >=0.11.0
Requires-Dist: h5py >=3.10.0
Requires-Dist: setuptools >=61.0
Requires-Dist: pandas >=2.0.3
